qtconsole/__init__.py
qtconsole/__main__.py
qtconsole/_version.py
qtconsole/ansi_code_processor.py
qtconsole/base_frontend_mixin.py
qtconsole/bracket_matcher.py
qtconsole/call_tip_widget.py
qtconsole/client.py
qtconsole/comms.py
qtconsole/completion_html.py
qtconsole/completion_plain.py
qtconsole/completion_widget.py
qtconsole/console_widget.py
qtconsole/frontend_widget.py
qtconsole/history_console_widget.py
qtconsole/inprocess.py
qtconsole/ipython_widget.py
qtconsole/jupyter_widget.py
qtconsole/kernel_mixins.py
qtconsole/kill_ring.py
qtconsole/mainwindow.py
qtconsole/manager.py
qtconsole/pygments_highlighter.py
qtconsole/qstringhelpers.py
qtconsole/qtconsoleapp.py
qtconsole/rich_ipython_widget.py
qtconsole/rich_jupyter_widget.py
qtconsole/rich_text.py
qtconsole/styles.py
qtconsole/svg.py
qtconsole/usage.py
qtconsole/util.py
qtconsole/resources/icon/JupyterConsole.svg
qtconsole/tests/__init__.py
qtconsole/tests/test_00_console_widget.py
qtconsole/tests/test_ansi_code_processor.py
qtconsole/tests/test_app.py
qtconsole/tests/test_comms.py
qtconsole/tests/test_completion_widget.py
qtconsole/tests/test_frontend_widget.py
qtconsole/tests/test_inprocess_kernel.py
qtconsole/tests/test_jupyter_widget.py
qtconsole/tests/test_kill_ring.py
qtconsole/tests/test_styles.py
qtconsole-5.6.0.dist-info/LICENSE
qtconsole-5.6.0.dist-info/METADATA
qtconsole-5.6.0.dist-info/WHEEL
qtconsole-5.6.0.dist-info/entry_points.txt
qtconsole-5.6.0.dist-info/top_level.txt
qtconsole-5.6.0.dist-info/RECORD
