Metadata-Version: 2.1
Name: qtconsole
Version: 5.6.0
Summary: Jupyter Qt console
Home-page: http://jupyter.org
Author: Jupyter Development Team
Author-email: jupyter@googlegroups.com
Maintainer: Spyder Development Team
License: BSD
Keywords: Interactive,Interpreter,Shell
Platform: Linux
Platform: Mac OS X
Platform: Windows
Classifier: Intended Audience :: Developers
Classifier: Intended Audience :: System Administrators
Classifier: Intended Audience :: Science/Research
Classifier: License :: OSI Approved :: BSD License
Classifier: Programming Language :: Python
Classifier: Programming Language :: Python :: 3
Classifier: Programming Language :: Python :: 3.8
Classifier: Programming Language :: Python :: 3.9
Classifier: Programming Language :: Python :: 3.10
Classifier: Programming Language :: Python :: 3.11
Classifier: Programming Language :: Python :: 3.12
Requires-Python: >= 3.8
License-File: LICENSE
Requires-Dist: traitlets!=5.2.1,!=5.2.2
Requires-Dist: jupyter_core
Requires-Dist: jupyter_client>=4.1
Requires-Dist: pygments
Requires-Dist: ipykernel>=4.1
Requires-Dist: qtpy>=2.4.0
Requires-Dist: packaging
Provides-Extra: test
Requires-Dist: flaky; extra == "test"
Requires-Dist: pytest; extra == "test"
Requires-Dist: pytest-qt; extra == "test"
Provides-Extra: doc
Requires-Dist: Sphinx>=1.3; extra == "doc"
